py_near/__init__.py
py_near/account.py
py_near/constants.py
py_near/models.py
py_near/providers.py
py_near/transactions.py
py_near/utils.py
py_near/dapps/__init__.py
py_near/dapps/core.py
py_near/dapps/fts.py
py_near/dapps/ft/__init__.py
py_near/dapps/ft/async_client.py
py_near/dapps/ft/exceptions.py
py_near/dapps/ft/models.py
py_near/dapps/nft/__init__.py
py_near/dapps/nft/models.py
py_near/exceptions/__init__.py
py_near/exceptions/exceptions.py
py_near/exceptions/provider.py
py_near/mpc/__init__.py
py_near/mpc/models.py
py_near/mpc/wallet.py
py_near/mpc/auth/__init__.py
py_near/mpc/auth/auth_2fa.py
py_near/mpc/auth/base.py
py_near/mpc/auth/core.py
py_near/mpc/auth/default_auth.py
py_near/mpc/auth/keys_auth.py
py_near/omni_balance/__init__.py
py_near/omni_balance/constants.py
py_near/omni_balance/exceptions.py
py_near/omni_balance/manager.py
py_near/omni_balance/models.py
py_near/omni_balance/solver/__init__.py
py_near/omni_balance/solver/core.py
py_near/omni_balance/solver/quote.py
py_near/omni_balance/solver/solver.py
py_near/omni_balance/solver/solver_bus_client.py
py_near/omni_balance/solver/solver_fix_rate.py
py_near-1.2.20.dist-info/licenses/LICENSE
py_near-1.2.20.dist-info/METADATA
py_near-1.2.20.dist-info/WHEEL
py_near-1.2.20.dist-info/top_level.txt
py_near-1.2.20.dist-info/RECORD
