Metadata-Version: 2.4
Name: py-near
Version: 1.2.20
Summary: Async client for NEAR Blockchain with native HOT Protocol & NEAR Intents support
Author-email: pvolnov <peter@hot-labs.org>
License: Permission is hereby granted, free of charge, to any
Project-URL: homepage, https://github.com/pvolnov/py-near
Project-URL: documentation, https://py-near.readthedocs.io/en/latest
Project-URL: repository, https://github.com/pvolnov/py-near
Project-URL: changelog, https://github.com/pvolnov/py-near/blob/main/CHANGELOG.md
Project-URL: funding, https://opencollective.com/py-near
Project-URL: twitter, https://twitter.com/p_volnov
Keywords: python,near,async
Classifier: Programming Language :: Python :: 3
Classifier: Programming Language :: Python :: 3.9
Classifier: Programming Language :: Python :: 3.10
Classifier: Programming Language :: Python :: 3.11
Classifier: License :: OSI Approved :: MIT License
Classifier: Operating System :: OS Independent
Requires-Python: <4,>=3.9
License-File: LICENSE
Requires-Dist: base58>=2.1.1
Requires-Dist: frozenlist>=1.4.1
Requires-Dist: pynacl>=1.5.0
Requires-Dist: loguru>=0.7.2
Requires-Dist: pydantic>=2.6.2
Requires-Dist: eth-keys>=0.7.0
Requires-Dist: aiohttp>=3.9.5
Requires-Dist: py-near-primitives==0.2.12
Dynamic: license-file
